AUTHORS
INSTALL
LICENSE
MANIFEST.in
README.rst
setup.py
django_rauthall.egg-info/PKG-INFO
django_rauthall.egg-info/SOURCES.txt
django_rauthall.egg-info/dependency_links.txt
django_rauthall.egg-info/not-zip-safe
django_rauthall.egg-info/requires.txt
django_rauthall.egg-info/top_level.txt
docs/Makefile
docs/source/conf.py
docs/source/index.rst
rauthall/__init__.py
rauthall/admin.py
rauthall/forms.py
rauthall/models.py
rauthall/tests.py
rauthall/urls.py
rauthall/views.py
rauthall/migrations/0001_initial.py
rauthall/migrations/0002_auto__chg_field_userprofile_user.py
rauthall/migrations/__init__.py
rauthall/templates/rauthall/profile.html